openapi_spec_tools/__init__.py
openapi_spec_tools/api_gen/_environment.py
openapi_spec_tools/api_gen/api_generator.py
openapi_spec_tools/api_gen/files.py
openapi_spec_tools/api_gen/flat_generator.py
openapi_spec_tools/api_gen/opaque_generator.py
openapi_spec_tools/api_gen/property_generator.py
openapi_spec_tools/base_gen/_logging.py
openapi_spec_tools/base_gen/_requests.py
openapi_spec_tools/base_gen/base_generator.py
openapi_spec_tools/base_gen/constants.py
openapi_spec_tools/base_gen/files.py
openapi_spec_tools/base_gen/utils.py
openapi_spec_tools/cli/api_gen.py
openapi_spec_tools/cli/arguments.py
openapi_spec_tools/cli/cli_gen.py
openapi_spec_tools/cli/layout.py
openapi_spec_tools/cli/oas.py
openapi_spec_tools/cli/utils.py
openapi_spec_tools/cli_gen/_arguments.py
openapi_spec_tools/cli_gen/_display.py
openapi_spec_tools/cli_gen/_exceptions.py
openapi_spec_tools/cli_gen/_tree.py
openapi_spec_tools/cli_gen/cli_generator.py
openapi_spec_tools/cli_gen/constants.py
openapi_spec_tools/cli_gen/files.py
openapi_spec_tools/layout/layout_generator.py
openapi_spec_tools/layout/types.py
openapi_spec_tools/layout/utils.py
openapi_spec_tools/types.py
openapi_spec_tools/utils.py
tests/cli_gen/__init__.py
tests/cli_gen/helpers.py
tests/cli_gen/test_cli_generator.py
tests/cli_gen/test_display.py
tests/cli_gen/test_exceptions.py
tests/cli_gen/test_files.py
tests/cli_gen/test_main.py
tests/cli_gen/test_tree.py
openapi_spec_tools-0.9.9.dist-info/METADATA
openapi_spec_tools-0.9.9.dist-info/WHEEL
openapi_spec_tools-0.9.9.dist-info/entry_points.txt
openapi_spec_tools-0.9.9.dist-info/licenses/LICENSE
openapi_spec_tools-0.9.9.dist-info/RECORD
